odoo10_addon_mrp_operating_unit-10.0.1.0.0.99.dev3-py2.7-nspkg.pth
odoo/addons/mrp_operating_unit/README.rst
odoo/addons/mrp_operating_unit/__init__.py
odoo/addons/mrp_operating_unit/__manifest__.py
odoo/addons/mrp_operating_unit/models/__init__.py
odoo/addons/mrp_operating_unit/models/mrp.py
odoo/addons/mrp_operating_unit/models/procurement.py
odoo/addons/mrp_operating_unit/security/mrp_security.xml
odoo/addons/mrp_operating_unit/static/description/icon.png
odoo/addons/mrp_operating_unit/tests/__init__.py
odoo/addons/mrp_operating_unit/tests/test_mrp_operating_unit.py
odoo/addons/mrp_operating_unit/tests/test_procurement.py
odoo/addons/mrp_operating_unit/views/mrp_view.xml
odoo10_addon_mrp_operating_unit-10.0.1.0.0.99.dev3.dist-info/METADATA
odoo10_addon_mrp_operating_unit-10.0.1.0.0.99.dev3.dist-info/RECORD
odoo10_addon_mrp_operating_unit-10.0.1.0.0.99.dev3.dist-info/WHEEL
odoo10_addon_mrp_operating_unit-10.0.1.0.0.99.dev3.dist-info/namespace_packages.txt
odoo10_addon_mrp_operating_unit-10.0.1.0.0.99.dev3.dist-info/top_level.txt
