Metadata-Version: 2.1
Name: odoo10-addon-mrp-operating-unit
Version: 10.0.1.0.0.99.dev3
Summary: Operating Unit in MRP
Home-page: http://www.eficent.com
Author: Eficent Business and IT Consulting Services S.L., Serpent Consulting Services Pvt. Ltd.,Odoo Community Association (OCA)
Author-email: support@odoo-community.org
License: LGPL-3
Platform: UNKNOWN
Classifier: Programming Language :: Python
Classifier: Framework :: Odoo
Classifier: License :: OSI Approved :: GNU Lesser General Public License v3 (LGPLv3)
Requires-Python: ~=2.7
Requires-Dist: odoo10-addon-procurement-operating-unit
Requires-Dist: odoo (<10.1dev,>=10.0)
